gen_cw/__init__.py
gen_cw/abbrevs.dict
gen_cw/combination.dict
gen_cw/connectives.dict
gen_cw/names.dict
gen_cw/words.dict
wordsworth-0.1.5.dist-info/METADATA
wordsworth-0.1.5.dist-info/WHEEL
wordsworth-0.1.5.dist-info/entry_points.txt
wordsworth-0.1.5.dist-info/top_level.txt
wordsworth-0.1.5.dist-info/RECORD
