Metadata-Version: 2.1
Name: wordsworth
Version: 0.1.5
Summary: Wordsworth Morse code exercises for fldigi
Home-page: https://0x9900.com/learning-cw/
Author: Fred C. (W6BSD)
Author-email: w6bsd@bsdworld.org
License: BSD
Project-URL: Source, https://github.com/0x9900/wordsworth/
Project-URL: Tracker, https://github.com/0x9900/wordsworth/issues
Platform: UNKNOWN
Classifier: Development Status :: 3 - Alpha
Classifier: Intended Audience :: Developers
Classifier: License :: OSI Approved :: BSD License
Classifier: Operating System :: OS Independent
Classifier: Programming Language :: Python
Classifier: Programming Language :: Python :: 3
Classifier: Programming Language :: Python :: 3.5
Classifier: Topic :: Communications :: Ham Radio
